{
  "generator-jhipster": {
    "applicationType": "microservice",
    "gitCompany": "",
    "baseName": "restoauth",
    "packageName": "ro.siveco.jhipster",
    "packageFolder": "ro/siveco/jhipster",
    "serverPort": 8081,
    "serviceDiscoveryType": "eureka",
    "authenticationType": "oauth2",
    "uaaBaseName": "../uaa",
    "cacheProvider": "ehcache",
    "enableHibernateCache": true,
    "websocket": false,
    "databaseType": "sql",
    "devDatabaseType": "h2Disk",
    "prodDatabaseType": "postgresql",
    "searchEngine": false,
    "enableSwaggerCodegen": false,
    "messageBroker": false,
    "buildTool": "maven",
    "useSass": true,
    "clientPackageManager": "npm",
    "testFrameworks": [],
    "enableTranslation": false,
    "nativeLanguage": "en",
    "languages": [
      "en"
    ],
    "clientFramework": "angularX",
    "jhiPrefix": "jhi",
    "jhipsterVersion": "6.4.1",
    "embeddableLaunchScript": false,
    "entitySuffix": "",
    "dtoSuffix": "DTO",
    "otherModules": [],
    "blueprints": [],
    "skipClient": true,
    "skipUserManagement": true
  },
  "git-provider": "GitHub",
  "git-company": "ActionAdi83",
  "repository-name": "restoauth"
}